[
  {
    "pool_address": "0x2f16faa9f152cb21b6c9ce02fef5dbdf9ae469b4",
    "gauge_address": "",
    "symbol": "WBNB/BDEFIV2",
    "name": "UniV2 - WBNB/BDEFIV2",
    "protocol": "Saitama",
    "pairType": "uniswapv2",
    "isStable": "",
    "token0": "0xbb4cdb9cbd36b01bd1cbaebf2de08d9173bc095c",
    "token1": "0xe078118fd1ec3e96750ab30bb32bb7aaf95d42d4",
    "token0_symbol": "WBNB",
    "token1_symbol": "BDEFIV2",
    "token0_name": "Wrapped BNB",
    "token1_name": "Blokdefi V2",
    "token0_decimals": 18,
    "token1_decimals": 18
  },
  {
    "pool_address": "0xe91d6c04723f9c9a66f72b8a4046b74b2155c0c6",
    "gauge_address": "",
    "symbol": "WBNB/FOF",
    "name": "UniV2 - WBNB/FOF",
    "protocol": "Saitama",
    "pairType": "uniswapv2",
    "isStable": "",
    "token0": "0xbb4cdb9cbd36b01bd1cbaebf2de08d9173bc095c",
    "token1": "0xf0fcf7602c4722ad4cbc1b1d8bf8b3a79ee4c8e1",
    "token0_symbol": "WBNB",
    "token1_symbol": "FOF",
    "token0_name": "Wrapped BNB",
    "token1_name": "Flame Of Floki",
    "token0_decimals": 18,
    "token1_decimals": 18
  },
  {
    "pool_address": "0x9be0b9da092a225d24bf0bc591392d69a42c348b",
    "gauge_address": "",
    "symbol": "WBNB/NEOM",
    "name": "UniV2 - WBNB/NEOM",
    "protocol": "Saitama",
    "pairType": "uniswapv2",
    "isStable": "",
    "token0": "0xbb4cdb9cbd36b01bd1cbaebf2de08d9173bc095c",
    "token1": "0xf4ddbff9fc214e8369f693eff1e1b0d558b4faf2",
    "token0_symbol": "WBNB",
    "token1_symbol": "NEOM",
    "token0_name": "Wrapped BNB",
    "token1_name": "Neom",
    "token0_decimals": 18,
    "token1_decimals": 18
  },
  {
    "pool_address": "0x7fed8d36567fa037fe11eaf283a84a38ae3e4c9f",
    "gauge_address": "",
    "symbol": "BDEFI/WBNB",
    "name": "UniV2 - BDEFI/WBNB",
    "protocol": "Saitama",
    "pairType": "uniswapv2",
    "isStable": "",
    "token0": "0xacb0bdcd50636a8552e5cf05a5d4d5716c5f6e60",
    "token1": "0xbb4cdb9cbd36b01bd1cbaebf2de08d9173bc095c",
    "token0_symbol": "BDEFI",
    "token1_symbol": "WBNB",
    "token0_name": "Blokdefi",
    "token1_name": "Wrapped BNB",
    "token0_decimals": 18,
    "token1_decimals": 18
  },
  {
    "pool_address": "0xc2caff9e5d23b3acb6bfea56af66d36e065e3fe8",
    "gauge_address": "",
    "symbol": "BDEFI/WBNB",
    "name": "UniV2 - BDEFI/WBNB",
    "protocol": "Saitama",
    "pairType": "uniswapv2",
    "isStable": "",
    "token0": "0x38f7f7189f4f0756d98321d9bbf5d06d25a16866",
    "token1": "0xbb4cdb9cbd36b01bd1cbaebf2de08d9173bc095c",
    "token0_symbol": "BDEFI",
    "token1_symbol": "WBNB",
    "token0_name": "Blokdefi",
    "token1_name": "Wrapped BNB",
    "token0_decimals": 18,
    "token1_decimals": 18
  },
  {
    "pool_address": "0xb057f5728a5f08a3eef20585ec4ab231f6294c88",
    "gauge_address": "",
    "symbol": "TruMaga/WBNB",
    "name": "UniV2 - TruMaga/WBNB",
    "protocol": "Saitama",
    "pairType": "uniswapv2",
    "isStable": "",
    "token0": "0x328ea6e5ba4cc4b58799f2aec3d8ba839f4314ba",
    "token1": "0xbb4cdb9cbd36b01bd1cbaebf2de08d9173bc095c",
    "token0_symbol": "TruMaga",
    "token1_symbol": "WBNB",
    "token0_name": "TrumpMaga",
    "token1_name": "Wrapped BNB",
    "token0_decimals": 18,
    "token1_decimals": 18
  },
  {
    "pool_address": "0x9a1fe623a793fc8bb4eaa9c5f575d0ee9490c23c",
    "gauge_address": "",
    "symbol": "AIM/WBNB",
    "name": "UniV2 - AIM/WBNB",
    "protocol": "Saitama",
    "pairType": "uniswapv2",
    "isStable": "",
    "token0": "0x48e5751930248e02c978648620cc4fd3f7924c00",
    "token1": "0xbb4cdb9cbd36b01bd1cbaebf2de08d9173bc095c",
    "token0_symbol": "AIM",
    "token1_symbol": "WBNB",
    "token0_name": "Token",
    "token1_name": "Wrapped BNB",
    "token0_decimals": 18,
    "token1_decimals": 18
  },
  {
    "pool_address": "0x7d84cd298ab1cb4da58f9aac2b19ac2de5b1e895",
    "gauge_address": "",
    "symbol": "WBNB/STCB",
    "name": "UniV2 - WBNB/STCB",
    "protocol": "Saitama",
    "pairType": "uniswapv2",
    "isStable": "",
    "token0": "0xbb4cdb9cbd36b01bd1cbaebf2de08d9173bc095c",
    "token1": "0xe5c3029c20a0e5bba2ca778efd9cea9980f0abdc",
    "token0_symbol": "WBNB",
    "token1_symbol": "STCB",
    "token0_name": "Wrapped BNB",
    "token1_name": "SaitaChain Burn",
    "token0_decimals": 18,
    "token1_decimals": 18
  },
  {
    "pool_address": "0x08e2353ea78fbdae13830bce5ec3a7cf6403ed9f",
    "gauge_address": "",
    "symbol": "Fire/WBNB",
    "name": "UniV2 - Fire/WBNB",
    "protocol": "Saitama",
    "pairType": "uniswapv2",
    "isStable": "",
    "token0": "0x3f49567be28fde4dd90b3f648027e60013a0a2bd",
    "token1": "0xbb4cdb9cbd36b01bd1cbaebf2de08d9173bc095c",
    "token0_symbol": "Fire",
    "token1_symbol": "WBNB",
    "token0_name": "Fireball",
    "token1_name": "Wrapped BNB",
    "token0_decimals": 18,
    "token1_decimals": 18
  },
  {
    "pool_address": "0x29401d4ef288ffb68733ee7985a72ebe844b323b",
    "gauge_address": "",
    "symbol": "WBNB/FLOKI",
    "name": "UniV2 - WBNB/FLOKI",
    "protocol": "Saitama",
    "pairType": "uniswapv2",
    "isStable": "",
    "token0": "0xbb4cdb9cbd36b01bd1cbaebf2de08d9173bc095c",
    "token1": "0xfb5b838b6cfeedc2873ab27866079ac55363d37e",
    "token0_symbol": "WBNB",
    "token1_symbol": "FLOKI",
    "token0_name": "Wrapped BNB",
    "token1_name": "FLOKI",
    "token0_decimals": 18,
    "token1_decimals": 9
  },
  {
    "pool_address": "0x84fa89c2acf79591f36812b1728b904e6630a2a9",
    "gauge_address": "",
    "symbol": "MOTN/WBNB",
    "name": "UniV2 - MOTN/WBNB",
    "protocol": "Saitama",
    "pairType": "uniswapv2",
    "isStable": "",
    "token0": "0x5def381f3a069ecd90ae69361f61d96bd9f3ad70",
    "token1": "0xbb4cdb9cbd36b01bd1cbaebf2de08d9173bc095c",
    "token0_symbol": "MOTN",
    "token1_symbol": "WBNB",
    "token0_name": "Motion Token",
    "token1_name": "Wrapped BNB",
    "token0_decimals": 18,
    "token1_decimals": 18
  },
  {
    "pool_address": "0x78ace9745977908ab337bd3ccc9878e99565068d",
    "gauge_address": "",
    "symbol": "Cake/WBNB",
    "name": "UniV2 - Cake/WBNB",
    "protocol": "Saitama",
    "pairType": "uniswapv2",
    "isStable": "",
    "token0": "0x0e09fabb73bd3ade0a17ecc321fd13a19e81ce82",
    "token1": "0xbb4cdb9cbd36b01bd1cbaebf2de08d9173bc095c",
    "token0_symbol": "Cake",
    "token1_symbol": "WBNB",
    "token0_name": "PancakeSwap Token",
    "token1_name": "Wrapped BNB",
    "token0_decimals": 18,
    "token1_decimals": 18
  },
  {
    "pool_address": "0xa6007fce56d5506a10df176101e3ec36c3f80e68",
    "gauge_address": "",
    "symbol": "WBNB/SRLTY",
    "name": "UniV2 - WBNB/SRLTY",
    "protocol": "Saitama",
    "pairType": "uniswapv2",
    "isStable": "",
    "token0": "0xbb4cdb9cbd36b01bd1cbaebf2de08d9173bc095c",
    "token1": "0xee8ed80bb013325ea63df19233aae584e94f3826",
    "token0_symbol": "WBNB",
    "token1_symbol": "SRLTY",
    "token0_name": "Wrapped BNB",
    "token1_name": "SaitaRealty",
    "token0_decimals": 18,
    "token1_decimals": 9
  },
  {
    "pool_address": "0xc4176c7367ba654268fef96c21be33b5b96df07d",
    "gauge_address": "",
    "symbol": "USDT/WBNB",
    "name": "UniV2 - USDT/WBNB",
    "protocol": "Saitama",
    "pairType": "uniswapv2",
    "isStable": "",
    "token0": "0x55d398326f99059ff775485246999027b3197955",
    "token1": "0xbb4cdb9cbd36b01bd1cbaebf2de08d9173bc095c",
    "token0_symbol": "USDT",
    "token1_symbol": "WBNB",
    "token0_name": "Tether USD",
    "token1_name": "Wrapped BNB",
    "token0_decimals": 18,
    "token1_decimals": 18
  },
  {
    "pool_address": "0xe29ba9023b76588ba563a3d1450def351c165ae4",
    "gauge_address": "",
    "symbol": "STC/WBNB",
    "name": "UniV2 - STC/WBNB",
    "protocol": "Saitama",
    "pairType": "uniswapv2",
    "isStable": "",
    "token0": "0x19ae49b9f38dd836317363839a5f6bfbfa7e319a",
    "token1": "0xbb4cdb9cbd36b01bd1cbaebf2de08d9173bc095c",
    "token0_symbol": "STC",
    "token1_symbol": "WBNB",
    "token0_name": "SaitaChain",
    "token1_name": "Wrapped BNB",
    "token0_decimals": 9,
    "token1_decimals": 18
  },
  {
    "pool_address": "0x59ba9ebafa00f70c41604d194d272c9cf120b926",
    "gauge_address": "",
    "symbol": "WBNB/STC",
    "name": "UniV2 - WBNB/STC",
    "protocol": "Saitama",
    "pairType": "uniswapv2",
    "isStable": "",
    "token0": "0xbb4cdb9cbd36b01bd1cbaebf2de08d9173bc095c",
    "token1": "0xbbf6fe62570eb952c1e3784991a24095b3093511",
    "token0_symbol": "WBNB",
    "token1_symbol": "STC",
    "token0_name": "Wrapped BNB",
    "token1_name": "SaitaChain",
    "token0_decimals": 18,
    "token1_decimals": 9
  },
  {
    "pool_address": "0x14697c2e9ad1b177f1ae3047b4e5a8b362ef48d8",
    "gauge_address": "",
    "symbol": "STC/WBNB",
    "name": "UniV2 - STC/WBNB",
    "protocol": "Saitama",
    "pairType": "uniswapv2",
    "isStable": "",
    "token0": "0x75907456105c1c3eb424f795b9772456701fc766",
    "token1": "0xbb4cdb9cbd36b01bd1cbaebf2de08d9173bc095c",
    "token0_symbol": "STC",
    "token1_symbol": "WBNB",
    "token0_name": "SaitaChain",
    "token1_name": "Wrapped BNB",
    "token0_decimals": 9,
    "token1_decimals": 18
  },
  {
    "pool_address": "0x9ec4533d239d08c55f0e3c8c2fda7c748140fae5",
    "gauge_address": "",
    "symbol": "WBNB/STC",
    "name": "UniV2 - WBNB/STC",
    "protocol": "Saitama",
    "pairType": "uniswapv2",
    "isStable": "",
    "token0": "0xbb4cdb9cbd36b01bd1cbaebf2de08d9173bc095c",
    "token1": "0xe091d951250ae77b14c5020254dabd5d79d3715d",
    "token0_symbol": "WBNB",
    "token1_symbol": "STC",
    "token0_name": "Wrapped BNB",
    "token1_name": "SaitaChain",
    "token0_decimals": 18,
    "token1_decimals": 9
  },
  {
    "pool_address": "0x335532d73e9fdbc7fa054697c63b1bcf52cd4835",
    "gauge_address": "",
    "symbol": "HARDROCK/SBS",
    "name": "UniV2 - HARDROCK/SBS",
    "protocol": "Saitama",
    "pairType": "uniswapv2",
    "isStable": "",
    "token0": "0x2980dac7aa0070ee668becf03235dd5c851f6e4e",
    "token1": "0xe00d6a16834e70cb6684cb979b68f5602dfecfb2",
    "token0_symbol": "HARDROCK",
    "token1_symbol": "SBS",
    "token0_name": "HARDROCK",
    "token1_name": "STARBUCKS",
    "token0_decimals": 18,
    "token1_decimals": 18
  },
  {
    "pool_address": "0xbe05dc78491b044090d6daf52556deeb941befcc",
    "gauge_address": "",
    "symbol": "EMJOY/WBNB",
    "name": "UniV2 - EMJOY/WBNB",
    "protocol": "Saitama",
    "pairType": "uniswapv2",
    "isStable": "",
    "token0": "0x63a129d999b8a9043b9ca31c04b6bb825f438140",
    "token1": "0xbb4cdb9cbd36b01bd1cbaebf2de08d9173bc095c",
    "token0_symbol": "EMJOY",
    "token1_symbol": "WBNB",
    "token0_name": "EMOJI JOY",
    "token1_name": "Wrapped BNB",
    "token0_decimals": 18,
    "token1_decimals": 18
  },
  {
    "pool_address": "0x8e59953ac2a6b0b4008f6287cee25adee0739517",
    "gauge_address": "",
    "symbol": "XRP/WBNB",
    "name": "UniV2 - XRP/WBNB",
    "protocol": "Saitama",
    "pairType": "uniswapv2",
    "isStable": "",
    "token0": "0x1d2f0da169ceb9fc7b3144628db156f3f6c60dbe",
    "token1": "0xbb4cdb9cbd36b01bd1cbaebf2de08d9173bc095c",
    "token0_symbol": "XRP",
    "token1_symbol": "WBNB",
    "token0_name": "XRP Token",
    "token1_name": "Wrapped BNB",
    "token0_decimals": 18,
    "token1_decimals": 18
  },
  {
    "pool_address": "0xf473db5c69b8898ff4de696e1c63b9b762c61ab3",
    "gauge_address": "0x4a341549ddA03de4C8277BAB0932900A0312EcbF",
    "chefPid": 1,
    "symbol": "Mazi/WBNB",
    "name": "UniV2 - Mazi/WBNB",
    "protocol": "Saitama",
    "pairType": "uniswapv2",
    "isStable": "",
    "token0": "0x5b8650cd999b23cf39ab12e3213fbc8709c7f5cb",
    "token1": "0xbb4cdb9cbd36b01bd1cbaebf2de08d9173bc095c",
    "token0_symbol": "Mazi",
    "token1_symbol": "WBNB",
    "token0_name": "Mazimatic",
    "token1_name": "Wrapped BNB",
    "token0_decimals": 18,
    "token1_decimals": 18
  },
  {
    "pool_address": "0x18711f546eebd0afcac0bb4d2b7d10645fa19c5e",
    "gauge_address": "",
    "symbol": "DOGE/WBNB",
    "name": "UniV2 - DOGE/WBNB",
    "protocol": "Saitama",
    "pairType": "uniswapv2",
    "isStable": "",
    "token0": "0xba2ae424d960c26247dd6c32edc70b295c744c43",
    "token1": "0xbb4cdb9cbd36b01bd1cbaebf2de08d9173bc095c",
    "token0_symbol": "DOGE",
    "token1_symbol": "WBNB",
    "token0_name": "Dogecoin",
    "token1_name": "Wrapped BNB",
    "token0_decimals": 8,
    "token1_decimals": 18
  },
  {
    "pool_address": "0x29855d4346ac5c33879cd6d859d0ce44a87328a7",
    "gauge_address": "0x4a341549ddA03de4C8277BAB0932900A0312EcbF",
    "chefPid": 0,
    "symbol": "Mazi/WBNB",
    "name": "UniV2 - Mazi/WBNB",
    "protocol": "Saitama",
    "pairType": "uniswapv2",
    "isStable": "",
    "token0": "0x5b8650cd999b23cf39ab12e3213fbc8709c7f5cb",
    "token1": "0xbb4cdb9cbd36b01bd1cbaebf2de08d9173bc095c",
    "token0_symbol": "Mazi",
    "token1_symbol": "WBNB",
    "token0_name": "Mazimatic",
    "token1_name": "Wrapped BNB",
    "token0_decimals": 18,
    "token1_decimals": 18
  },
  {
    "pool_address": "0x666f695dd95dc864a5b9c9ae1f5aed6c088b1908",
    "gauge_address": "",
    "symbol": "XRP/WBNB",
    "name": "UniV2 - XRP/WBNB",
    "protocol": "Saitama",
    "pairType": "uniswapv2",
    "isStable": "",
    "token0": "0x1d2f0da169ceb9fc7b3144628db156f3f6c60dbe",
    "token1": "0xbb4cdb9cbd36b01bd1cbaebf2de08d9173bc095c",
    "token0_symbol": "XRP",
    "token1_symbol": "WBNB",
    "token0_name": "XRP Token",
    "token1_name": "Wrapped BNB",
    "token0_decimals": 18,
    "token1_decimals": 18
  },
  {
    "pool_address": "0x4b1e184573e36e97dc08daa7bce3dd1e5176c47a",
    "gauge_address": "",
    "symbol": "DOGE/WBNB",
    "name": "UniV2 - DOGE/WBNB",
    "protocol": "Saitama",
    "pairType": "uniswapv2",
    "isStable": "",
    "token0": "0xba2ae424d960c26247dd6c32edc70b295c744c43",
    "token1": "0xbb4cdb9cbd36b01bd1cbaebf2de08d9173bc095c",
    "token0_symbol": "DOGE",
    "token1_symbol": "WBNB",
    "token0_name": "Dogecoin",
    "token1_name": "Wrapped BNB",
    "token0_decimals": 8,
    "token1_decimals": 18
  },
  {
    "pool_address": "0xf14c072a85eb770870ff33b88fa531d8d1667b7b",
    "gauge_address": "",
    "symbol": "WBNB/BUSD",
    "name": "UniV2 - WBNB/BUSD",
    "protocol": "Saitama",
    "pairType": "uniswapv2",
    "isStable": "",
    "token0": "0xbb4cdb9cbd36b01bd1cbaebf2de08d9173bc095c",
    "token1": "0xe9e7cea3dedca5984780bafc599bd69add087d56",
    "token0_symbol": "WBNB",
    "token1_symbol": "BUSD",
    "token0_name": "Wrapped BNB",
    "token1_name": "BUSD Token",
    "token0_decimals": 18,
    "token1_decimals": 18
  }
]